README.md
setup.cfg
setup.py
remote_sqlite/__init__.py
remote_sqlite.egg-info/PKG-INFO
remote_sqlite.egg-info/SOURCES.txt
remote_sqlite.egg-info/dependency_links.txt
remote_sqlite.egg-info/requires.txt
remote_sqlite.egg-info/top_level.txt