Metadata-Version: 2.1
Name: remote-sqlite
Version: 1.1.1
Summary: RemoteSqlite is a way to easily access a remote Sqlite database and perform queries
Home-page: https://github.com/vbalasu/RemoteSqlite
Author: Vijay Balasubramaniam
Author-email: your.email@domain.com
License: MIT
Download-URL: https://github.com/vbalasu/RemoteSqlite/archive/v1.1.tar.gz
Keywords: sqlite3,remote
Platform: UNKNOWN
Classifier: Development Status :: 5 - Production/Stable
Classifier: Intended Audience :: Developers
Classifier: Topic :: Software Development :: Build Tools
Classifier: License :: OSI Approved :: MIT License
Classifier: Programming Language :: Python :: 3
Classifier: Programming Language :: Python :: 3.4
Classifier: Programming Language :: Python :: 3.5
Classifier: Programming Language :: Python :: 3.6
Classifier: Programming Language :: Python :: 3.7
